macss_tallies/__init__.py
macss_tallies/main.py
macss_tallies/utils.py
macss_tallies-0.0.5.dist-info/DESCRIPTION.rst
macss_tallies-0.0.5.dist-info/METADATA
macss_tallies-0.0.5.dist-info/RECORD
macss_tallies-0.0.5.dist-info/WHEEL
macss_tallies-0.0.5.dist-info/entry_points.txt
macss_tallies-0.0.5.dist-info/metadata.json
macss_tallies-0.0.5.dist-info/top_level.txt
