Metadata-Version: 2.0
Name: macss-tallies
Version: 0.0.5
Summary: UNKNOWN
Home-page: https://github.com/reidmcy/MACSS-Workshop-Tallies
Author: Reid McIlroy-Young
Author-email: reidmcy@uchicago.edu
License: GPL
Download-URL: https://github.com/reidmcy/MACSS-Workshop-Tallies/archive/0.0.5.tar.gz
Keywords: MACSS
Platform: UNKNOWN
Classifier: Development Status :: 3 - Alpha
Classifier: Environment :: Console
Classifier: Environment :: MacOS X
Classifier: Intended Audience :: Science/Research
Classifier: License :: OSI Approved :: GNU General Public License v2 (GPLv2)
Classifier: Operating System :: MacOS :: MacOS X
Classifier: Operating System :: POSIX
Classifier: Operating System :: Microsoft :: Windows
Classifier: Programming Language :: Python :: 3 :: Only
Classifier: Topic :: Education
Requires-Dist: datetime
Requires-Dist: requests
